{
  "faqs": {
    "游戏下载更新说明": "1。推荐从谷歌市场下载安装原版\u003cbr\u003e\u003cbr\u003e2。没有谷歌账号的，可以用\u003ca href\u003dhttps://aurorastore.org\u003e极光应用商店\u003c/a\u003e匿名从谷歌市场下载安装\u003cbr\u003e\u003cbr\u003e3。中国区域用户，可以下载\u003cfont color\u003d\"#ff\"\u003e\u003ca href\u003dhttps://share.feijipan.com/s/QMHuh4gc\u003e【网盘分享：动作分类】\u003c/a\u003e\u003c/font\u003e里的安装包，搬运自谷歌市场的原版",
    "\u003cfont color\u003d\"#ff0000\"\u003e常见问题解答\u003c/font\u003e": "1。中国区玩家，登录游戏后黑屏10到30秒左右就可以进入游戏了，不用担心是游戏卡住或出问题了，仅仅是出国网络差而已\u003cbr\u003e\u003cbr\u003e2.如果你的墨魔豆可以正常玩，桌面版本闪退，一般是因为游戏强制使用谷歌服务，你的设备没有谷歌服务导致闪退，\u003cfont color\u003d\"#ff\"\u003e使用MOD + 墨魔豆的虚拟谷歌服务\u003c/font\u003e，就可以跳过谷歌服务验证"
  },
  "gms": 2,
  "info": "游戏特色：\u003cbr\u003e-酣畅淋漓的击杀体验，经典动作肉鸽元素\u003cbr\u003e-引人入胜的战斗系统，极具节奏感的连招机制\u003cbr\u003e-多种卓越的英雄角色，独特的技能设定与差异化战斗风格\u003cbr\u003e-超140+被动能力，搭配天赋与符文系统，打造自定义的升级路线\u003cbr\u003e-充满挑战的随机地下城，3大章节与刺激的Boss战\u003cbr\u003e-浓厚的黑暗手绘风格，动态光影效果与沉浸式闯关氛围\u003cbr\u003e-丰富的故事情节，了解深渊更深处的秘密\u003cbr\u003e-单机畅玩，可搭配丝滑的手柄操控",
  "label": "深渊之影：国际版",
  "time": 1761004800008,
  "mod": true,
  "mods": [
    {
      "descs": [
        "【可选菜单】战场上可自由更换付费角色，变更金币收益率、消费折扣、技能无CD、无伤、随意掉落武器道具"
      ],
      "name": "上帝模式",
      "pkgname": "com.chillyroom.sotd.gp.gm64",
      "sandbox": 155,
      "targetvc": "*",
      "vercode": 4
    }
  ],
  "pkgname": "com.chillyroom.sotd.gp",
  "vercode": 84,
  "vername": "1.1.8",
  "publisher": "凉屋（ChillyRoom）",
  "s1": [
    512,
    1024,
    2048
  ],
  "s2": [
    2048,
    6144,
    10904
  ],
  "s3": 4608,
  "search": [
    "战魂铭人",
    "元气骑士"
  ],
  "tags": [
    "中文",
    "国际版",
    "肉鸽",
    "动作"
  ],
  "downloads": [
    {
      "host": "网盘分享：动作分类",
      "url": "https://share.feijipan.com/s/QMHuh4gc",
      "var": false
    }
  ]
}