{
  "gms": 1,
  "info": "● 深受数百万玩家喜爱的游戏机制！玩三消游戏，装饰花园，同时体验精彩剧情！\u003cbr\u003e● 超过 16000 个令人爱不释手的关卡，另有爆炸加速道具、实用增强道具和酷炫的关卡元素。\u003cbr\u003e● 精彩活动！踏上精彩的探险之旅，在各式各样的挑战中与其他玩家比拼，赢取丰厚奖品！\u003cbr\u003e● 独一无二的花园区域，布局独特，从喷泉景观到岛屿景观。\u003cbr\u003e● 许多个性独特的角色：认识奥斯汀的朋友和邻居！\u003cbr\u003e● 可爱的宠物将成为你忠实的伙伴！\u003cbr\u003e\u003cbr\u003e在游戏社区中结交新朋友！",
  "label": "梦幻花园",
  "time": 1778025600008,
  "lastProm": 0,
  "lastRec": 0,
  "mod": true,
  "mods": [
    {
      "descs": [
        "【可选菜单】金币收益率、道具无消耗、加速"
      ],
      "name": "休闲模式",
      "pkgname": "com.playrix.gardenscapes.gm64",
      "sandbox": 155,
      "targetvc": "109600",
      "vercode": 27
    }
  ],
  "pkgname": "com.playrix.gardenscapes",
  "vercode": 109600,
  "vername": "9.6.0",
  "publisher": "Playrix",
  "s1": [
    512,
    1024,
    2048
  ],
  "s2": [
    2048,
    4096,
    8192
  ],
  "s3": 4096,
  "extra": 0,
  "install": 2,
  "mod_tvc": 2,
  "source": 1,
  "tags": [
    "中文",
    "休闲",
    "三消"
  ],
  "downloads": [
    {
      "host": "网盘分享 ➡ 休闲分类 ➡ 三消类别",
      "url": "https://share.feijipan.com/s/QMHuh4gc",
      "var": false
    }
  ]
}